vqls_prototype/__init__.py
vqls_prototype/__version__.py
vqls_prototype/hadamard_test/direct_hadamard_test.py
vqls_prototype/hadamard_test/hadamard_overlap_test.py
vqls_prototype/hadamard_test/hadamard_test.py
vqls_prototype/matrix_decomposition/__init__.py
vqls_prototype/matrix_decomposition/matrix_decomposition.py
vqls_prototype/matrix_decomposition/optimized_matrix_decomposition.py
vqls_prototype/solver/__init__.py
vqls_prototype/solver/base_solver.py
vqls_prototype/solver/hybrid_qst_vqls.py
vqls_prototype/solver/log.py
vqls_prototype/solver/qst_vqls.py
vqls_prototype/solver/variational_linear_solver.py
vqls_prototype/solver/vqls.py
vqls_prototype/tomography/__init__.py
vqls_prototype/tomography/htree_qst.py
vqls_prototype/tomography/nnqst.py
vqls_prototype/tomography/qst.py
vqls_prototype/tomography/shadow_qst.py
vqls_prototype/tomography/simulator_qst.py
vqls_prototype-0.2.0.dist-info/LICENSE.txt
vqls_prototype-0.2.0.dist-info/METADATA
vqls_prototype-0.2.0.dist-info/WHEEL
vqls_prototype-0.2.0.dist-info/top_level.txt
vqls_prototype-0.2.0.dist-info/RECORD
