Metadata-Version: 2.1
Name: vqls-prototype
Version: 0.2.0
Summary: Repository for a quantum prototype
Author-email: Nicolas Renaud <nicolas.gm.renaud@gmail.com>
License: Copyright 2021 IBM and its contributors
Project-URL: Homepage, https://github.com/qiskit-community/quantum-prototype-template
Project-URL: Bug Tracker, https://github.com/qiskit-community/quantum-prototype-template/issues
Requires-Python: >=3.8
License-File: LICENSE.txt
Requires-Dist: certifi >=2021.5.30
Requires-Dist: importlib-metadata >=4.8.1
Requires-Dist: qiskit-aer >=0.10.3
Requires-Dist: qiskit >=0.14.1
Requires-Dist: qiskit-experiments >=0.5.3
Requires-Dist: qiskit-ibm-runtime >=0.9.3
Requires-Dist: ipykernel >=6.15.0
Requires-Dist: matplotlib >=3.5.3
Requires-Dist: pylatexenc >=2.10
Requires-Dist: tqdm >=4.64.1
Requires-Dist: networkx >=2.8.4
Requires-Dist: sparse >=0.14.0
Requires-Dist: treelib
Provides-Extra: dev
Requires-Dist: coverage >=5.5 ; extra == 'dev'
Requires-Dist: pylint >=2.9.5 ; extra == 'dev'
Requires-Dist: nbqa >=1.1.1 ; extra == 'dev'
Requires-Dist: treon >=0.1.3 ; extra == 'dev'
Requires-Dist: pytest >=6.2.5 ; extra == 'dev'
Requires-Dist: pytest-randomly >=1.2.0 ; extra == 'dev'
Requires-Dist: mypy >=0.780 ; extra == 'dev'
Requires-Dist: mypy-extensions >=0.4.3 ; extra == 'dev'
Requires-Dist: jupyter-sphinx >=0.3.2 ; extra == 'dev'
Requires-Dist: nbsphinx >=0.8.8 ; extra == 'dev'
Requires-Dist: sphinx-autodoc-typehints >=1.17.0 ; extra == 'dev'
Requires-Dist: qiskit-sphinx-theme ~=1.16.0 ; extra == 'dev'
Requires-Dist: reno >=3.5.0 ; extra == 'dev'
Requires-Dist: black[jupyter] ~=22.1 ; extra == 'dev'
